gui/__init__.py
gui/components.py
gui/reader.py
console_gui-0.0.5.dist-info/LICENSE
console_gui-0.0.5.dist-info/METADATA
console_gui-0.0.5.dist-info/WHEEL
console_gui-0.0.5.dist-info/top_level.txt
console_gui-0.0.5.dist-info/RECORD
