Metadata-Version: 2.1
Name: console-gui
Version: 0.0.5
Summary: gui for conosle buttons and fields
Home-page: UNKNOWN
Author: levi dalrymple
License: MIT License
Platform: UNKNOWN
Classifier: Development Status :: 1 - Planning
Classifier: Environment :: Console
Classifier: Operating System :: Microsoft :: Windows
Classifier: Programming Language :: Python :: 3.4
Classifier: Programming Language :: Python :: 3.5
License-File: LICENSE
Requires-Dist: colorama
Requires-Dist: pynput
